<?xml version="1.0" encoding="UTF-8"?>
<Column size="full">
    <Row color="#fcfcfc" size="expand" class="border-end">
        {% block west %}
        {% endblock %}
    </Row>
    <Container size="fluid" padding="p-0" margin="m-0" class="d-flex flex-column container-fluid">
        <Container size="fluid" color="#fcfcfc" class="border-bottom">
            {% block north %}
            {% endblock %}
        </Container>
        <Container>
            {% block center %}
            {% endblock %}
        </Container>
        <Container size="fluid" color="#fcfcfc" margin="mt-auto" class="border-top">
            {% block south %}
            {% endblock %}
        </Container>
    </Container>
    <Row color="#fcfcfc" width="253px" size="expand" class="border-start">
        {% block east %}
        {% endblock %}
    </Row>
</Column>